_kaldifst.cp312-win32.pyd
kaldifst_core.dll
kaldifst_core.lib
kaldifst_fst.dll
kaldifst_fst.lib
kaldifst_fstscript.dll
kaldifst_fstscript.lib
kaldifst/__init__.py
kaldifst/iterator.py
kaldifst/lattice_to_nbest.py
kaldifst/table_types.py
kaldifst/bin/kaldifst_core.dll
kaldifst/bin/kaldifst_core.lib
kaldifst/bin/kaldifst_fst.dll
kaldifst/bin/kaldifst_fst.lib
kaldifst/bin/kaldifst_fstscript.dll
kaldifst/bin/kaldifst_fstscript.lib
kaldifst/lib/kaldifst_fst.dll
kaldifst/lib/kaldifst_fst.lib
kaldifst/utils/__init__.py
kaldifst/utils/k2_converter.py
kaldifst-1.7.17.dist-info/licenses/LICENSE
kaldifst-1.7.17.dist-info/METADATA
kaldifst-1.7.17.dist-info/WHEEL
kaldifst-1.7.17.dist-info/top_level.txt
kaldifst-1.7.17.dist-info/RECORD
