Metadata-Version: 2.1
Name: kaldifst
Version: 1.7.17
Home-page: https://github.com/k2-fsa/kaldifst
Author: Next-gen Kaldi development team
Author-email: csukuangfj@gmail.com
License: Apache-2.0
Classifier: Programming Language :: C++
Classifier: Programming Language :: Python
Classifier: Topic :: Scientific/Engineering :: Artificial Intelligence
Requires-Python: >=3.8
License-File: LICENSE
